Workbook

Sheet CAPA
C5: PLANILHA PARA SOLICITAÇÃO DE CANCELAMENTO DE CARTÕES
D8: Resumo da solicitação de cancelamento cartão:
D10: Data envio solicitação
D11: Caixa
D12: Nro da Venda
D13: Nome Estabelecimento
D14: Cód. ESTABELECIMENTO
D16: Nome do Cliente
D17: CPF do Cliente
D19: Modalidade Cancelamento
D20: Número cartão a cancelar | E20: =IF(TRANSACAO!D12="","",TRANSACAO!D12)
D22: Valor transação do cartão
D23: Valor a cancelar no cartão

Sheet TRANSACAO
C2: SEQ | D2: DATA | E2: CX | F2: VALOR | G2: ABATIMENTO | H2: JUROS | I2: MULTA | J2: TOTAL GERAL | K2: TIPO LIQ | L2: OP CONTABIL | M2: N PARCELAS | N2: TEF-NSU | O2: WEB-NSU | P2: TID
E8: ="4" & TEXT(INT(D8),"yymmdd") -> 4000100
C9: Data
C10: Loja
C11: Codigo Loja
C12: Cartao
C13: PDV
C14: NSU
C15: NSU Host
C16: Valor
C17: Rede
C18: Tipo Produto
C19: Conciliacao
C20: Codigo Autorizacao
... C33: Descricao da Loja

Sheet DADOSDR
B2: CIELO
B3: DATA SOLIC | C3: CX | D3: N° DA VENDA | E3: NOME DA UO | F3: NOME DO CLIENTE | G3: CPF CLIENTE | H3: DATA DA VENDA TRANSAÇÃO | I3: VALOR TOTAL DA VENDA | J3: VALOR DA TRANSAÇÃO FEITA NO CARTÃO | K3: QTE PARC | L3: BANDEIRA | M3: NSU | N3: CÓD AUT | O3: TID | P3: VALOR CANCELADO
B4: =IF(CAPA!E10="","",CAPA!E10) | C4: =IF(CAPA!E11="","",CAPA!E11) | D4: =IF(CAPA!E12="","",CAPA!E12) | E4: =IF(CAPA!E13="","",CAPA!E13) | F4: =IF(CAPA!E16="","",CAPA!E16) | G4: =IF(CAPA!E17="","",CAPA!E17) | H4: =D12 -> 0 | I4: =TRANSACAO!J3 -> 0 | J4: =G12 -> 0 | K4: =H8 -> 0 | L4: =TRANSACAO!D24 -> 0 | M4: =VALUE(TRANSACAO!D13) -> 0 | N4: =I12 -> 0 | O4: =TRANSACAO!P3 | P4: =H12 -> 0 | T4: CANCELAMENTO STD | U4: EFETIVADO
B6: BANRI
B7: N° DA VENDA | C7: VALOR TOTAL DA VENDA | D7: CPF DO CLIENTE | E7: NOME DO CLIENTE | F7: NOME DA UO | G7: VALOR DA TRANSAÇÃO E DO CANCELAMENTO | H7: QTE PARC | I7: BANDEIRA | J7: NSU | K7: NSU BERGS | L7: TID | M7: DATA DE ENVIO DE CANCELAMENTO | N7: DATA DA EFETIVAÇÃO DO CANCELAMENTO | O7: LANÇ SESC NET | P7: STATUS | Q7: OBS
B8: =CAPA!E12 -> 0 | C8: =CAPA!E22 -> 0 | D8: =G4 | E8: =F4 | F8: =E4 | G8: =CAPA!E22 -> 0 | H8: =TRANSACAO!D26 -> 0 | I8: =TRANSACAO!D24 -> 0 | J8: =TRANSACAO!D13 -> 0 | K8: =J8 -> 0 | L8: =O4 | M8: =CAPA!E10 -> 0
B11: ESTABELECIMENTO | C11: LOTE | D11: DT DEPÓSITO | E11: CARTÃO / XID | F11: DT VENDA | G11: VL VENDA | H11: VL CANCELAR | I11: AUT. | J11: MOTIVO
B12: =CAPA!E14 -> 0 | C12: =TRANSACAO!E8 -> 4000100 | D12: =TRANSACAO!D8 -> 0 | E12: =TRANSACAO!D11 -> 0 | F12: =D12 -> 0 | G12: =IF(TRANSACAO!D15<>"",TRANSACAO!D15,TRANSACAO!J3) -> 0 | H12: =CAPA!E23 -> 0 | I12: =TRANSACAO!D20 -> 0 | J12: A pedido do cliente
B16: INFORMAÇÕES PARA CANCELAMENTO VERO - PREENCHIMENTO AUTOMÁTICO
B17: CNPJ | C17: =IFERROR(VLOOKUP(CAPA!E14,Planilha1!A:C,3,TRUE),"")
B18: DATA DA VENDA | C18: =IFERROR(G12,"") -> 0
B19: VALOR DA VENDA | C19: =IFERROR(#REF!,"")
B20: VALOR CANCELAMENTO | C20: =H12 -> 0
B21: NSU BERGS | C21: =K8 -> 0
B22: CÓDIGO LÓGICO | C22: =VLOOKUP(CAPA!E14,Planilha1!A:D,4,0) -> #N/A
B23: Nº CARTÃO | C23: =E12 -> 0
B24: Nº PARCELAS | C24: =H8 -> 0
B25: TÍTULO | C25: =CAPA!E12 -> 0

Sheet Planilha1
B3: ESTABELECIMENTO DO SESC/RS | C3: CNPJ | D3: CÓDIGO LÓGICO
A4: 1006957020 | B4: SESC 4º DISTRITO | C4: 03.575.238/0003-03 | D4: 41123700000300
A5: 2778065800 | B5: SESC ALBERTO BINS - RESTAURANTE | C5: 03.575.238/0069-21 | D5: 41123700006900
A6: 1006956740 | B6: SESC AZENHA | C6: 03.575.238/0005-67 | D6: 41123700000500
A7: 2895942891 | B7: SESC ANCHIETA | C7: 03.575.238/0085-41 | D7: 41123700008500
A8: 1006957003 | B8: SESC ALEGRETE | C8: 03.575.238/0025-00 | D8: 41123700002500
A9: 1015704848 | B9: SESC BAGE | C9: 03.575.238/0023-49 | D9: 41123700002300
A10: 2778140896 | B10: SESC BENTO GONÇALVES | C10: 03.575.238/0046-35 | D10: 41123700004600
A11: 1014953569 | B11: SESC CACHOEIRA DO SUL | C11: 03.575.238/0013-77 | D11: 41123700001300
A12: 1034211312 | B12: SESC CACHOEIRINHA | C12: 03.575.238/0041-20 | D12: 41123700004100
A13: 1015704988 | B13: SESC CAMAQUÃ | C13: 03.575.238/0029-34 | D13: 41123700002900
A14: 1059465350 | B14: SESC CANOAS | C14: 03.575.238/0040-40 | D14: 41123700004000
A15: 1006957046 | B15: SESC CARAZINHO | C15: 03.575.238/0021-87 | D15: 41123700002100
... A31: 1012411971 | B31: SESC MONTENEGRO | C31: 03.575.238/0031-59 | D31: 41123700003100
A32: 2900505741 | B32: SESC NOVA PRATA | C32: 03.575.238/0088-94 | D32: BANRIS
A33: 1006956899 | B33: SESC NOVO HAMBURGO | C33: 03.575.238/0017-09 | D33: 41123700001700
A34: 1096168615 | B34: SESC OSÓRIO | C34: 03.575.238/0050-11 | D34: 41123700005000
A35: 1096168607 | B35: SESC PALMEIRA DAS MISSÕES | C35: 03.575.238/0049-88 | D35: 41123700004900
A36: 1006963020 | B36: SESC PASSO FUNDO | C36: 03.575.238/0020-04 | D36: 41123700002000
A37: 1006956880 | B37: SESC PELOTAS | C37: 03.575.238/0014-58 | D37: 41123700001400
A38: 1005526823 | B38: SESC PROTÁSIO ALVES - HOTEL | C38: 03.575.238/0002-14 | D38: 41123700000200
A39: 2897596974 | B39: SESC QUARAÍ | C39: 03.575.238/0081-18 | D39: 41123700008100
A40: 1014327900 | B40: SESC RIO GRANDE | C40: 03.575.238/0019-62 | D40: 41123700001900
A41: 1006956961 | B41: SESC SANTA CRUZ DO SUL | C41: 03.575.238/0010-24 | D41: 41123700001000
A42: 1006957143 | B42: SESC SANTA MARIA | C42: 03.575.238/0009-90 | D42: 41123700000900
A43: 1006957135 | B43: SESC SANTA ROSA | C43: 03.575.238/0026-91 | D43: 41123700002600
A44: 1012412013 | B44: SESC SANTANA DO LIVRAMENTO | C44: 03.575.238/0022-68 | D44: 41123700002200
... A51: 1096168658 | B51: SESC SÃO SEPÉ | C51: 03.575.238/0064-17 | D51: 41123700006400
A52: 2898427327 | B52: SESC SÃO JUDAS | C52: 03.575.238/0089-75
A53: 1006956708 | B53: SESC SEDE | C53: 03.575.238/0001-33 | D53: 41123700000100
A54: 2897203069 | B54: SESC TRES DE MAIO EJA | C54: 03.575.238/0090-09 | D54: 41123700009000
A55: 2898296923 | B55: SESC TRES PASSOS | C55: 03.575.238/0083-80 | D55: 41123700008300
A56: 1014327862 | B56: SESC TAQUARA | C56: 03.575.238/0034-00 | D56: 41123700003400
A57: 1012195470 | B57: SESC TORRES - HOTEL | C57: 03.575.238/0030-78 | D57: 41123700003000
A58: 1027418330 | B58: SESC TRAMANDAÍ | C58: 03.575.238/0037-44 | D58: 41123700003700
A59: 1067221244 | B59: SESC TRÊS DE MAIO | C59: 03.575.238/0055-26 | D59: 41123700005500
A60: 1006957097 | B60: SESC URUGUAIANA | C60: 03.575.238/0007-29 | D60: 41123700000700
A61: 1067221252 | B61: SESC VACARIA | C61: 03.575.238/0063-36 | D61: 41123700006300
A62: 1045331691 | B62: SESC VIAMÃO | C62: 03.575.238/0038-25 | D62: 41123700003800
A63: 1012369401 | B63: SESC VENANCIO AIRES | C63: 03.575.238/0032-30 | D63: 41123700003200

Sheet Simulador
B2: CÁLCULO VENDAS CANCELADAS CARTÃO DE CREDITO - MENSAL/PLANOS | I2: ***Somente os campos em amarelo devem ser preenchidos pela UO. | O2: 1 | P2: 1 | Q2: MENSAL
B3: descrição | C3: valor | D3: valor mês/dia | E3: quantidade mês/dias | F3: multa | G3: cobrança | I3: Selecione, abaixo, a opção desejada. | O3: 2 | P3: 2 | Q3: TRIMESTRAL
B4: Mensal | D4: =ROUND(VALUE(C4)/E4,2) -> 0 | E4: 30 | F4: não | G4: dias | I4: ANUAL | O4: 3 | P4: 5 | Q4: TRIMESTRAL
B5: Trimestral | D5: =ROUND(VALUE(C5)/3,2) -> 0 | E5: 3 | F5: sim | G5: mês integral | I5: =VLOOKUP(I4,#REF!,2,0) -> #REF! | J5: =SUM(J13,G10) -> 0 | O5: 6 | P5: 6 | Q5: SEMESTRAL
B6: Semestral | D6: =ROUND(VALUE(C6)/6,2) -> 0 | E6: 6 | F6: sim | G6: mês integral | O6: 7 | P6: 12 | Q6: ANUAL
B7: Anual | D7: =ROUND(VALUE(C7)/12,2) -> 0 | E7: 12 | F7: sim | G7: mês integral
B9: MENSAL | C9: data da venda | D9: Data do cancelamento | E9: Dias disponibilizados | F9: Valor dias disponibilizados | G9: =IF(G10>=0, "Devolução ao Cliente","Gerar Nota de Crédito") -> Devolução ao Cliente
E10: =IF(D10="","",IFERROR(D10-C10,"")) | F10: =IF(D10="","",IFERROR(D4*E10,"")) | G10: =IF(D10="","",IFERROR(C4-F10,""))
L11: SIM
A12: =IF(A13=1,"Trimestral",IF(A13=2,"Semestral",IF(A13=3,"Anual",""))) | B12: Plano (trimestral, semestral e anual) | C12: Data da venda | D12: Data do cancelamento | E12: Meses disponibilizados | F12: Multa mês | G12: Valor multa | H12: valor do serviço disponibilizado | I12: Valor serv. disponibilizado + multa | J12: =IF(IFERROR(IF(J13<=0,"Valor a receber do cliente",IF(J13>0,"Valor a devolver para o cliente")),"")=FALSE(),"",IFERROR(IF(J13<=0,"Valor a receber do cliente",IF(J13>0,"Valor a devolver para o cliente")),"")) -> Valor a devolver para o cliente | L12: O valor da multa será descontado do valor a devolver?
A13: =IFERROR(IF(I5=2,1,IF(I5=3,2,IF(I5=4,3))),"") | B13: =A12 | C13: 45870 | D13: 46006 | E13: =IFERROR(IF(AND(C13="", D13=""), "", SUM(DATEDIF(C13,D13,"M")+1)),"") -> 5 | F13: =IF(D13="","",IFERROR(IF(A12="TRIMESTRAL",C4-D5,IF(A12="SEMESTRAL",C4-D6,IF(A12="ANUAL",C4-D7))),"")) -> FALSE | G13: =IFERROR(F13*E13,"") -> 0 | H13: =IFERROR(IF(A12="TRIMESTRAL",D5*E13,IF(A12="SEMESTRAL",D6*E13,IF(A12="ANUAL",D7*E13))),"") -> FALSE | I13: =IFERROR(IF(L13="Não", 0, G13+H13),"") -> 0 | J13: =IFERROR(IF(L13=2,IF(A12="trimestral",C5-H13,IF(A12="semestral",C6-H13,IF(A12="anual",C7-H13))),IF(A12="trimestral",C5-I13,IF(A12="semestral",C6-I13,IF(A12="anual",C7-I13)))),"") -> FALSE | L13: =IFERROR(VLOOKUP(L11,#REF!,2,0),"")
B17: CÁLCULO VENDAS CANCELADAS CARTÃO DE CRÉDITO - RECORRÊNCIA
A18: =IF(A19=1,"trimestral",IF(A19=2,"semestral",IF(A19=3,"anual",""))) -> #REF! | B18: Plano (trimestral, semestral e anual) | C18: Data da venda | D18: Data do cancelamento | E18: Valor do contrato | F18: Meses disponibilizados | G18: Multa/mês | H18: Valor total multa | I18: Valor do serviço pago
A19: =VLOOKUP(A20,#REF!,3,0) -> #REF! | E19: =IF(A19=1,VLOOKUP("Trimestral",B4:C7,2,0),IF(A19=2,VLOOKUP("Semestral",B4:C7,2,0),IF(A19=3,VLOOKUP("Anual",B4:C7,2,0)))) -> #REF! | F19: =IFERROR(IF(AND(C19="", D19=""), "", SUM(DATEDIF(C19,D19,"M")+1)),"") | G19: =IFERROR(IF(A18="TRIMESTRAL",C4-D5,IF(A18="SEMESTRAL",C4-D6,IF(A18="ANUAL",C4-D7))),"") | H19: =IFERROR(G19*F19,"") | I19: =IFERROR(IF(A18="TRIMESTRAL",D5*F19,IF(A18="SEMESTRAL",D6*F19,IF(A18="ANUAL",D7*F19))),"")
A20: ANUAL
